setup.cfg
setup.py
pyosci/__init__.py
pyosci/commands.py
pyosci/daq.py
pyosci/fit.py
pyosci/function_generators.py
pyosci/logging.py
pyosci/osci.py
pyosci/plotting.py
pyosci/powersupply.py
pyosci/pyoscidefault.mplstyle
pyosci/pyoscipresent.mplstyle
pyosci/tools.py
pyosci.egg-info/PKG-INFO
pyosci.egg-info/SOURCES.txt
pyosci.egg-info/dependency_links.txt
pyosci.egg-info/requires.txt
pyosci.egg-info/top_level.txt