Metadata-Version: 1.1
Name: pyosci
Version: 0.0.13
Summary: Readout a TektronixDPO4104B oscilloscope
Home-page: https://github.com/achim1/pyosci
Author: Achim Stoessl
Author-email: achim.stoessl@gmail.com
License: GPL
Keywords: oscilloscope,daq,TektronixDPO4104B,Tektronix,readout,physics,engineering,SCPI,VISA
Platform: Ubuntu 14.04
Platform: Ubuntu 16.04
Classifier: License :: OSI Approved :: GNU General Public License v3 or later (GPLv3+)
Classifier: Development Status :: 3 - Alpha
Classifier: Intended Audience :: Science/Research
Classifier: Intended Audience :: Developers
Classifier: Programming Language :: Python :: 3.5
Classifier: Topic :: Scientific/Engineering :: Physics
